{
  "__inputs": [],
  "__requires": [
    {
      "type": "panel",
      "id": "bargauge",
      "name": "Bar Gauge",
      "version": ""
    },
    {
      "type": "grafana",
      "id": "grafana",
      "name": "Grafana",
      "version": "6.4.4"
    },
    {
      "type": "panel",
      "id": "graph",
      "name": "Graph",
      "version": ""
    },
    {
      "type": "datasource",
      "id": "postgres",
      "name": "PostgreSQL",
      "version": "1.0.0"
    },
    {
      "type": "panel",
      "id": "singlestat",
      "name": "Singlestat",
      "version": ""
    },
    {
      "type": "panel",
      "id": "table",
      "name": "Table",
      "version": ""
    }
  ],
  "annotations": {
    "list": [
      {
        "builtIn": 1,
        "datasource": "-- Grafana --",
        "enable": true,
        "hide": true,
        "iconColor": "rgba(0, 211, 255, 1)",
        "name": "Annotations & Alerts",
        "type": "dashboard"
      }
    ]
  },
  "editable": true,
  "gnetId": null,
  "graphTooltip": 1,
  "id": null,
  "iteration": 1576947656770,
  "links": [],
  "panels": [
    {
      "aliasColors": {},
      "bars": false,
      "dashLength": 10,
      "dashes": false,
      "datasource": "$database",
      "fill": 0,
      "fillGradient": 0,
      "gridPos": {
        "h": 5,
        "w": 16,
        "x": 0,
        "y": 0
      },
      "id": 6,
      "legend": {
        "alignAsTable": true,
        "avg": false,
        "current": false,
        "max": false,
        "min": false,
        "rightSide": true,
        "show": false,
        "sort": "total",
        "sortDesc": true,
        "total": true,
        "values": true
      },
      "lines": false,
      "linewidth": 2,
      "links": [],
      "nullPointMode": "null",
      "options": {
        "dataLinks": []
      },
      "percentage": false,
      "pointradius": 5,
      "points": true,
      "renderer": "flot",
      "seriesOverrides": [],
      "spaceLength": 10,
      "stack": false,
      "steppedLine": false,
      "targets": [
        {
          "format": "time_series",
          "group": [],
          "metricColumn": "none",
          "rawQuery": true,
          "rawSql": "SELECT \r\n  MAX(table_name) AS metric,\r\n  to_timestamp(lower(ranges[1])/10^6) AS time,\r\n  SUM(total_bytes)\r\nFROM _timescaledb_catalog.hypertable, chunk_relation_size(table_name::text) \r\nWHERE \r\n  table_name LIKE 'metric%' \r\nGROUP BY time \r\nORDER BY metric, time;\r\n",
          "refId": "A",
          "select": [
            [
              {
                "params": [
                  "value"
                ],
                "type": "column"
              }
            ]
          ],
          "table": "metrics",
          "timeColumn": "\"time\"",
          "timeColumnType": "timestamp",
          "where": [
            {
              "name": "$__timeFilter",
              "params": [],
              "type": "macro"
            }
          ]
        }
      ],
      "thresholds": [],
      "timeFrom": null,
      "timeRegions": [],
      "timeShift": null,
      "title": "Chunk Size",
      "tooltip": {
        "shared": true,
        "sort": 2,
        "value_type": "individual"
      },
      "type": "graph",
      "xaxis": {
        "buckets": null,
        "mode": "time",
        "name": null,
        "show": true,
        "values": []
      },
      "yaxes": [
        {
          "format": "bytes",
          "label": null,
          "logBase": 1,
          "max": "4.e9",
          "min": "0",
          "show": true
        },
        {
          "format": "short",
          "label": null,
          "logBase": 1,
          "max": null,
          "min": null,
          "show": true
        }
      ],
      "yaxis": {
        "align": false,
        "alignLevel": null
      }
    },
    {
      "cacheTimeout": null,
      "colorBackground": false,
      "colorValue": true,
      "colors": [
        "#d44a3a",
        "rgba(237, 129, 40, 0.89)",
        "#299c46"
      ],
      "datasource": "$database",
      "decimals": 2,
      "format": "percentunit",
      "gauge": {
        "maxValue": 100,
        "minValue": 0,
        "show": false,
        "thresholdLabels": false,
        "thresholdMarkers": true
      },
      "gridPos": {
        "h": 3,
        "w": 2,
        "x": 16,
        "y": 0
      },
      "id": 17,
      "interval": null,
      "links": [],
      "mappingType": 1,
      "mappingTypes": [
        {
          "name": "value to text",
          "value": 1
        },
        {
          "name": "range to text",
          "value": 2
        }
      ],
      "maxDataPoints": 100,
      "nullPointMode": "connected",
      "nullText": null,
      "options": {},
      "postfix": "",
      "postfixFontSize": "50%",
      "prefix": "",
      "prefixFontSize": "50%",
      "rangeMaps": [
        {
          "from": "null",
          "text": "N/A",
          "to": "null"
        }
      ],
      "sparkline": {
        "fillColor": "rgba(31, 118, 189, 0.18)",
        "full": false,
        "lineColor": "rgb(31, 120, 193)",
        "show": false,
        "ymax": null,
        "ymin": null
      },
      "tableColumn": "compression_ratio",
      "targets": [
        {
          "format": "table",
          "group": [],
          "metricColumn": "none",
          "rawQuery": true,
          "rawSql": "SELECT\n  hypertable_name,\n  1 - AVG(pg_size_bytes(compressed_total_bytes)::float / pg_size_bytes(uncompressed_total_bytes)) AS compression_ratio\nFROM timescaledb_information.compressed_chunk_stats\nWHERE compression_status = 'Compressed'\nGROUP BY hypertable_name",
          "refId": "A",
          "select": [
            [
              {
                "params": [
                  "avg_load"
                ],
                "type": "column"
              }
            ]
          ],
          "table": "agg_instance_load",
          "timeColumn": "bucket",
          "timeColumnType": "timestamp",
          "where": [
            {
              "name": "$__timeFilter",
              "params": [],
              "type": "macro"
            }
          ]
        }
      ],
      "thresholds": "0.8,0.95",
      "timeFrom": null,
      "timeShift": null,
      "title": "Compression",
      "type": "singlestat",
      "valueFontSize": "80%",
      "valueMaps": [
        {
          "op": "=",
          "text": "N/A",
          "value": "null"
        }
      ],
      "valueName": "current"
    },
    {
      "cacheTimeout": null,
      "colorBackground": false,
      "colorValue": false,
      "colors": [
        "#299c46",
        "rgba(237, 129, 40, 0.89)",
        "#d44a3a"
      ],
      "datasource": "$database",
      "decimals": 1,
      "format": "bytes",
      "gauge": {
        "maxValue": 100,
        "minValue": 0,
        "show": false,
        "thresholdLabels": false,
        "thresholdMarkers": true
      },
      "gridPos": {
        "h": 3,
        "w": 3,
        "x": 18,
        "y": 0
      },
      "id": 15,
      "interval": null,
      "links": [],
      "mappingType": 1,
      "mappingTypes": [
        {
          "name": "value to text",
          "value": 1
        },
        {
          "name": "range to text",
          "value": 2
        }
      ],
      "maxDataPoints": 100,
      "nullPointMode": "connected",
      "nullText": null,
      "options": {},
      "postfix": "",
      "postfixFontSize": "50%",
      "prefix": "",
      "prefixFontSize": "50%",
      "rangeMaps": [
        {
          "from": "null",
          "text": "N/A",
          "to": "null"
        }
      ],
      "sparkline": {
        "fillColor": "rgba(31, 118, 189, 0.18)",
        "full": false,
        "lineColor": "rgb(31, 120, 193)",
        "show": false,
        "ymax": null,
        "ymin": null
      },
      "tableColumn": "",
      "targets": [
        {
          "format": "table",
          "group": [],
          "metricColumn": "none",
          "rawQuery": true,
          "rawSql": "SELECT prom_sql_size_total();\n",
          "refId": "A",
          "select": [
            [
              {
                "params": [
                  "avg_load"
                ],
                "type": "column"
              }
            ]
          ],
          "table": "agg_instance_load",
          "timeColumn": "bucket",
          "timeColumnType": "timestamp",
          "where": [
            {
              "name": "$__timeFilter",
              "params": [],
              "type": "macro"
            }
          ]
        }
      ],
      "thresholds": "",
      "timeFrom": null,
      "timeShift": null,
      "title": "Database Size",
      "type": "singlestat",
      "valueFontSize": "80%",
      "valueMaps": [
        {
          "op": "=",
          "text": "N/A",
          "value": "null"
        }
      ],
      "valueName": "current"
    },
    {
      "cacheTimeout": null,
      "colorBackground": false,
      "colorValue": false,
      "colors": [
        "#299c46",
        "rgba(237, 129, 40, 0.89)",
        "#d44a3a"
      ],
      "datasource": "$database",
      "decimals": 1,
      "format": "bytes",
      "gauge": {
        "maxValue": 100,
        "minValue": 0,
        "show": false,
        "thresholdLabels": false,
        "thresholdMarkers": true
      },
      "gridPos": {
        "h": 3,
        "w": 3,
        "x": 21,
        "y": 0
      },
      "id": 16,
      "interval": null,
      "links": [],
      "mappingType": 1,
      "mappingTypes": [
        {
          "name": "value to text",
          "value": 1
        },
        {
          "name": "range to text",
          "value": 2
        }
      ],
      "maxDataPoints": 100,
      "nullPointMode": "connected",
      "nullText": null,
      "options": {},
      "postfix": "",
      "postfixFontSize": "50%",
      "prefix": "",
      "prefixFontSize": "50%",
      "rangeMaps": [
        {
          "from": "null",
          "text": "N/A",
          "to": "null"
        }
      ],
      "sparkline": {
        "fillColor": "rgba(31, 118, 189, 0.18)",
        "full": false,
        "lineColor": "rgb(31, 120, 193)",
        "show": false,
        "ymax": null,
        "ymin": null
      },
      "tableColumn": "",
      "targets": [
        {
          "format": "table",
          "group": [],
          "metricColumn": "none",
          "rawQuery": true,
          "rawSql": "SELECT total_size FROM prom_sql_size_labels();",
          "refId": "A",
          "select": [
            [
              {
                "params": [
                  "avg_load"
                ],
                "type": "column"
              }
            ]
          ],
          "table": "agg_instance_load",
          "timeColumn": "bucket",
          "timeColumnType": "timestamp",
          "where": [
            {
              "name": "$__timeFilter",
              "params": [],
              "type": "macro"
            }
          ]
        }
      ],
      "thresholds": "",
      "timeFrom": null,
      "timeShift": null,
      "title": "Labels Size",
      "type": "singlestat",
      "valueFontSize": "80%",
      "valueMaps": [
        {
          "op": "=",
          "text": "N/A",
          "value": "null"
        }
      ],
      "valueName": "current"
    },
    {
      "datasource": "$database",
      "gridPos": {
        "h": 6,
        "w": 8,
        "x": 16,
        "y": 3
      },
      "id": 13,
      "options": {
        "displayMode": "lcd",
        "fieldOptions": {
          "calcs": [
            "sum"
          ],
          "defaults": {
            "mappings": [],
            "max": 80000000000,
            "min": 0,
            "thresholds": [
              {
                "color": "green",
                "value": null
              },
              {
                "color": "#EAB839",
                "value": 65000000000
              },
              {
                "color": "red",
                "value": 75000000000
              }
            ],
            "unit": "bytes"
          },
          "override": {},
          "values": false
        },
        "orientation": "horizontal"
      },
      "pluginVersion": "6.4.4",
      "targets": [
        {
          "format": "table",
          "group": [],
          "metricColumn": "none",
          "rawQuery": true,
          "rawSql": "SELECT * FROM prom_sql_size_samples();",
          "refId": "A",
          "select": [
            [
              {
                "params": [
                  "avg_load"
                ],
                "type": "column"
              }
            ]
          ],
          "table": "agg_instance_load",
          "timeColumn": "bucket",
          "timeColumnType": "timestamp",
          "where": [
            {
              "name": "$__timeFilter",
              "params": [],
              "type": "macro"
            }
          ]
        }
      ],
      "timeFrom": null,
      "timeShift": null,
      "title": "Database Size",
      "type": "bargauge"
    },
    {
      "aliasColors": {},
      "bars": false,
      "dashLength": 10,
      "dashes": false,
      "datasource": "$database",
      "fill": 1,
      "fillGradient": 0,
      "gridPos": {
        "h": 8,
        "w": 8,
        "x": 0,
        "y": 5
      },
      "id": 10,
      "legend": {
        "avg": false,
        "current": false,
        "max": false,
        "min": false,
        "show": true,
        "total": false,
        "values": false
      },
      "lines": true,
      "linewidth": 1,
      "nullPointMode": "null",
      "options": {
        "dataLinks": []
      },
      "percentage": false,
      "pluginVersion": "6.4.4",
      "pointradius": 2,
      "points": false,
      "renderer": "flot",
      "seriesOverrides": [],
      "spaceLength": 10,
      "stack": false,
      "steppedLine": false,
      "targets": [
        {
          "format": "time_series",
          "group": [],
          "metricColumn": "none",
          "rawQuery": true,
          "rawSql": "SELECT \n  $__timeGroup(time, '$__interval') AS time, \n  labels->>'pod' AS metric, \n  MAX(value) AS value\nFROM metrics \nWHERE \n  $__timeFilter(time) AND \n  name = 'adapter_connections_used_current'\nGROUP BY $__timeGroup(time, '$__interval'), metric\nORDER BY $__timeGroup(time, '$__interval'), metric",
          "refId": "A",
          "select": [
            [
              {
                "params": [
                  "delta_usage"
                ],
                "type": "column"
              }
            ]
          ],
          "table": "agg_container_cpu",
          "timeColumn": "bucket",
          "timeColumnType": "timestamp",
          "where": [
            {
              "name": "$__timeFilter",
              "params": [],
              "type": "macro"
            }
          ]
        }
      ],
      "thresholds": [],
      "timeFrom": null,
      "timeRegions": [],
      "timeShift": null,
      "title": "Active Conns",
      "tooltip": {
        "shared": true,
        "sort": 0,
        "value_type": "individual"
      },
      "type": "graph",
      "xaxis": {
        "buckets": null,
        "mode": "time",
        "name": null,
        "show": true,
        "values": []
      },
      "yaxes": [
        {
          "format": "short",
          "label": null,
          "logBase": 1,
          "max": null,
          "min": "0",
          "show": true
        },
        {
          "format": "short",
          "label": null,
          "logBase": 1,
          "max": null,
          "min": null,
          "show": true
        }
      ],
      "yaxis": {
        "align": false,
        "alignLevel": null
      }
    },
    {
      "aliasColors": {},
      "bars": false,
      "dashLength": 10,
      "dashes": false,
      "datasource": "$database",
      "fill": 1,
      "fillGradient": 1,
      "gridPos": {
        "h": 8,
        "w": 8,
        "x": 8,
        "y": 5
      },
      "id": 2,
      "legend": {
        "avg": false,
        "current": false,
        "max": false,
        "min": false,
        "show": true,
        "total": false,
        "values": false
      },
      "lines": true,
      "linewidth": 1,
      "nullPointMode": "null",
      "options": {
        "dataLinks": []
      },
      "percentage": false,
      "pluginVersion": "6.4.4",
      "pointradius": 2,
      "points": false,
      "renderer": "flot",
      "seriesOverrides": [],
      "spaceLength": 10,
      "stack": false,
      "steppedLine": false,
      "targets": [
        {
          "format": "time_series",
          "group": [],
          "metricColumn": "none",
          "rawQuery": true,
          "rawSql": "SELECT \n  metric, \n  bucket AS time, \n  rate_time(value, lag(value) OVER w, '$__interval') \nFROM (\nSELECT \n  labels->>'pod' AS metric, \n  $__timeGroup(time, '$__interval') AS bucket, \n  MAX(value) AS value\nFROM metrics \nWHERE \n  $__timeFilter(time) AND \n  name = 'adapter_labels_written_total' \nGROUP BY metric, bucket\nORDER BY metric, bucket\n) AS s \nWINDOW w AS (PARTITION BY s.metric ORDER BY s.bucket)",
          "refId": "A",
          "select": [
            [
              {
                "params": [
                  "delta_usage"
                ],
                "type": "column"
              }
            ]
          ],
          "table": "agg_container_cpu",
          "timeColumn": "bucket",
          "timeColumnType": "timestamp",
          "where": [
            {
              "name": "$__timeFilter",
              "params": [],
              "type": "macro"
            }
          ]
        }
      ],
      "thresholds": [],
      "timeFrom": null,
      "timeRegions": [],
      "timeShift": null,
      "title": "Active Labels",
      "tooltip": {
        "shared": true,
        "sort": 0,
        "value_type": "individual"
      },
      "type": "graph",
      "xaxis": {
        "buckets": null,
        "mode": "time",
        "name": null,
        "show": true,
        "values": []
      },
      "yaxes": [
        {
          "format": "short",
          "label": null,
          "logBase": 1,
          "max": null,
          "min": "0",
          "show": true
        },
        {
          "format": "short",
          "label": null,
          "logBase": 1,
          "max": null,
          "min": null,
          "show": true
        }
      ],
      "yaxis": {
        "align": false,
        "alignLevel": null
      }
    },
    {
      "columns": [],
      "datasource": "$database",
      "fontSize": "100%",
      "gridPos": {
        "h": 12,
        "w": 8,
        "x": 16,
        "y": 9
      },
      "id": 4,
      "options": {},
      "pageSize": null,
      "showHeader": true,
      "sort": {
        "col": 1,
        "desc": true
      },
      "styles": [
        {
          "alias": "",
          "colorMode": null,
          "colors": [
            "rgba(245, 54, 54, 0.9)",
            "rgba(237, 129, 40, 0.89)",
            "rgba(50, 172, 45, 0.97)"
          ],
          "dateFormat": "YYYY-MM-DD HH:mm:ss",
          "decimals": 2,
          "mappingType": 1,
          "pattern": "Time",
          "thresholds": [],
          "type": "hidden",
          "unit": "short"
        },
        {
          "alias": "",
          "colorMode": null,
          "colors": [
            "rgba(245, 54, 54, 0.9)",
            "rgba(237, 129, 40, 0.89)",
            "rgba(50, 172, 45, 0.97)"
          ],
          "decimals": 2,
          "pattern": "/.*/",
          "thresholds": [],
          "type": "number",
          "unit": "short"
        }
      ],
      "targets": [
        {
          "format": "table",
          "group": [],
          "metricColumn": "none",
          "rawQuery": true,
          "rawSql": "SELECT\n  relname AS metric,\n  n_live_tup AS value\nFROM pg_stat_all_tables\nORDER BY n_live_tup DESC\nLIMIT 50;",
          "refId": "A",
          "select": [
            [
              {
                "params": [
                  "value"
                ],
                "type": "column"
              }
            ]
          ],
          "table": "metrics",
          "timeColumn": "\"time\"",
          "timeColumnType": "timestamp",
          "where": [
            {
              "name": "$__timeFilter",
              "params": [],
              "type": "macro"
            }
          ]
        }
      ],
      "timeFrom": null,
      "timeShift": null,
      "title": "Live Tuples",
      "transform": "table",
      "type": "table"
    },
    {
      "aliasColors": {},
      "bars": false,
      "cacheTimeout": null,
      "dashLength": 10,
      "dashes": false,
      "datasource": "$database",
      "fill": 1,
      "fillGradient": 1,
      "gridPos": {
        "h": 8,
        "w": 8,
        "x": 0,
        "y": 13
      },
      "id": 11,
      "legend": {
        "avg": false,
        "current": false,
        "max": false,
        "min": false,
        "show": true,
        "total": false,
        "values": false
      },
      "lines": true,
      "linewidth": 1,
      "links": [],
      "nullPointMode": "null",
      "options": {
        "dataLinks": []
      },
      "percentage": false,
      "pluginVersion": "6.4.4",
      "pointradius": 2,
      "points": false,
      "renderer": "flot",
      "seriesOverrides": [],
      "spaceLength": 10,
      "stack": true,
      "steppedLine": true,
      "targets": [
        {
          "format": "time_series",
          "group": [],
          "metricColumn": "none",
          "rawQuery": true,
          "rawSql": "SELECT \n  $__timeGroup(time, '$__interval') AS time, \n  labels->>'pod' AS metric, \n  MAX(value) AS value\nFROM metrics \nWHERE \n  $__timeFilter(time) AND \n  name = 'adapter_connections_open_current'\nGROUP BY $__timeGroup(time, '$__interval'), metric\nORDER BY $__timeGroup(time, '$__interval'), metric",
          "refId": "A",
          "select": [
            [
              {
                "params": [
                  "delta_usage"
                ],
                "type": "column"
              }
            ]
          ],
          "table": "agg_container_cpu",
          "timeColumn": "bucket",
          "timeColumnType": "timestamp",
          "where": [
            {
              "name": "$__timeFilter",
              "params": [],
              "type": "macro"
            }
          ]
        }
      ],
      "thresholds": [],
      "timeFrom": null,
      "timeRegions": [],
      "timeShift": null,
      "title": "Open Conns",
      "tooltip": {
        "shared": true,
        "sort": 0,
        "value_type": "individual"
      },
      "type": "graph",
      "xaxis": {
        "buckets": null,
        "mode": "time",
        "name": null,
        "show": true,
        "values": []
      },
      "yaxes": [
        {
          "decimals": 0,
          "format": "short",
          "label": null,
          "logBase": 1,
          "max": null,
          "min": "0",
          "show": true
        },
        {
          "format": "short",
          "label": null,
          "logBase": 1,
          "max": null,
          "min": null,
          "show": true
        }
      ],
      "yaxis": {
        "align": false,
        "alignLevel": null
      }
    },
    {
      "aliasColors": {},
      "bars": false,
      "dashLength": 10,
      "dashes": false,
      "datasource": "$database",
      "fill": 1,
      "fillGradient": 1,
      "gridPos": {
        "h": 8,
        "w": 8,
        "x": 8,
        "y": 13
      },
      "id": 18,
      "legend": {
        "avg": false,
        "current": false,
        "max": false,
        "min": false,
        "show": true,
        "total": false,
        "values": false
      },
      "lines": true,
      "linewidth": 1,
      "nullPointMode": "null",
      "options": {
        "dataLinks": []
      },
      "percentage": false,
      "pluginVersion": "6.4.4",
      "pointradius": 2,
      "points": false,
      "renderer": "flot",
      "seriesOverrides": [],
      "spaceLength": 10,
      "stack": false,
      "steppedLine": false,
      "targets": [
        {
          "format": "time_series",
          "group": [],
          "metricColumn": "none",
          "rawQuery": true,
          "rawSql": "SELECT\n  labels->>'pod' AS metric,\n  time_bucket('$__interval', time) AS time,\n  MAX(value) AS value\nFROM metrics\nWHERE \n  name = 'adapter_labels_cache_current' AND \n  $__timeFilter(\"time\")\nGROUP BY time_bucket('$__interval', time), metric\nORDER BY time_bucket('$__interval', time), metric",
          "refId": "A",
          "select": [
            [
              {
                "params": [
                  "delta_usage"
                ],
                "type": "column"
              }
            ]
          ],
          "table": "agg_container_cpu",
          "timeColumn": "bucket",
          "timeColumnType": "timestamp",
          "where": [
            {
              "name": "$__timeFilter",
              "params": [],
              "type": "macro"
            }
          ]
        }
      ],
      "thresholds": [],
      "timeFrom": null,
      "timeRegions": [],
      "timeShift": null,
      "title": "Label Cache",
      "tooltip": {
        "shared": true,
        "sort": 0,
        "value_type": "individual"
      },
      "type": "graph",
      "xaxis": {
        "buckets": null,
        "mode": "time",
        "name": null,
        "show": true,
        "values": []
      },
      "yaxes": [
        {
          "format": "short",
          "label": null,
          "logBase": 1,
          "max": null,
          "min": "0",
          "show": true
        },
        {
          "format": "short",
          "label": null,
          "logBase": 1,
          "max": null,
          "min": null,
          "show": true
        }
      ],
      "yaxis": {
        "align": false,
        "alignLevel": null
      }
    }
  ],
  "refresh": "10s",
  "schemaVersion": 20,
  "style": "dark",
  "tags": [],
  "templating": {
    "list": [
      {
        "current": {
          "text": "monitor-timescale",
          "value": "monitor-timescale"
        },
        "hide": 0,
        "includeAll": false,
        "label": "Database",
        "multi": false,
        "name": "database",
        "options": [],
        "query": "postgres",
        "refresh": 1,
        "regex": ".*-timescale",
        "skipUrlSync": false,
        "type": "datasource"
      }
    ]
  },
  "time": {
    "from": "now-6h",
    "to": "now"
  },
  "timepicker": {
    "refresh_intervals": [
      "30s",
      "1m",
      "5m",
      "15m"
    ]
  },
  "timezone": "",
  "title": "Schema",
  "uid": "vEM91obZk",
  "version": 47
}